 [
  {
  "name": "Calculo Integral",
  "schedule": [
               "monday 7:00 am AG5",
               "tuesday 7:00 am AG5",
               "wednesday 7:00 am AG5",
               "thrusday 7:00 am AG5",
               "friday 7:00 am AG5"
               ]
  },
  
  {
  "name": "Programación orientada a objetos",
  "schedule": [
               "monday 8:00 am AG5",
               "tuesday 8:00 am AG5",
               "wednesday 8:00 am AG5",
               "thrusday 8:00 am AG5",
               "friday 8:00 am AG5"
               ]
  },
  {
  "name": "Matemáticas Discretas",
  "schedule": [
               "monday 9:00 am AG5",
               "tuesday 9:00 am AG5",
               "wednesday 9:00 am AG5",
               "thrusday 9:00 am AG5",
               "friday 9:00 am AG5"
               ]
  }
  ]
